quickrepo/__init__.py
quickrepo/version.py
quickrepo-1.0.5.dist-info/LICENSE
quickrepo-1.0.5.dist-info/METADATA
quickrepo-1.0.5.dist-info/WHEEL
quickrepo-1.0.5.dist-info/entry_points.txt
quickrepo-1.0.5.dist-info/top_level.txt
quickrepo-1.0.5.dist-info/RECORD
