Metadata-Version: 2.1
Name: quickrepo
Version: 1.0.5
Summary: Command-line tool to automate git and github repository creation.
Home-page: https://www.github.com/silverhairs/quickrepo
Author: Boris Kayi
Author-email: boriskayienzo@gmail.com
License: UNKNOWN
Platform: any
Classifier: Programming Language :: Python :: 3.6
Classifier: Programming Language :: Python :: 3.7
Classifier: Programming Language :: Python :: 3.8
Classifier: Intended Audience :: Developers
Classifier: Topic :: Software Development :: Build Tools
Classifier: License :: OSI Approved :: MIT License
Classifier: Operating System :: OS Independent
Requires-Python: >=3.6
Requires-Dist: click (==7.1.2)
Requires-Dist: click-spinner (==0.1.10)
Requires-Dist: PyGithub (==1.51)
Requires-Dist: GitPython (==3.1.3)
Requires-Dist: colorama (==0.4.3)
Provides-Extra: test
Requires-Dist: pytest (==5.4.3) ; extra == 'test'
